xueqiu/__init__.py
xueqiu/bin.py
xueqiu/core.py
xueqiu/version.json
xueqiu_client-1.0.0.dist-info/METADATA
xueqiu_client-1.0.0.dist-info/WHEEL
xueqiu_client-1.0.0.dist-info/entry_points.txt
xueqiu_client-1.0.0.dist-info/top_level.txt
xueqiu_client-1.0.0.dist-info/RECORD
