Metadata-Version: 2.1
Name: xueqiu-client
Version: 1.0.0
Summary: Client for Xueqiu.com
Home-page: https://github.com/suqingdong/xueqiu
Author: suqingdong
Author-email: suqingdong1114@gmail.com
License: MIT License
Platform: UNKNOWN
Classifier: Development Status :: 5 - Production/Stable
Classifier: Operating System :: OS Independent
Classifier: Intended Audience :: Developers
Classifier: License :: OSI Approved :: MIT License
Classifier: Programming Language :: Python
Classifier: Programming Language :: Python :: 3
Classifier: Programming Language :: Python :: 3.8
Classifier: Programming Language :: Python :: 3.9
Classifier: Programming Language :: Python :: 3.10
Classifier: Programming Language :: Python :: 3.11
Classifier: Programming Language :: Python :: 3.12
Classifier: Topic :: Software Development :: Libraries
Requires-Dist: click
Requires-Dist: plotext
Requires-Dist: requests
Requires-Dist: webrequests
Requires-Dist: prettytable
